{
  "unversionedId": "v5/order/batch-amend",
  "id": "v5/order/batch-amend",
  "title": "Batch Amend Order",
  "description": "This endpoint allows you to amend more than one open order in a single request.",
  "source": "@site/docs/v5/order/batch-amend.mdx",
  "sourceDirName": "v5/order",
  "slug": "/v5/order/batch-amend",
  "permalink": "/usa-docs/v5/order/batch-amend",
  "draft": false,
  "tags": [],
  "version": "current",
  "sidebarPosition": 8,
  "frontMatter": {
    "title": "Batch Amend Order",
    "sidebar_label": "Batch Amend Order",
    "sidebar_position": 8
  },
  "sidebar": "v5SideBar",
  "previous": {
    "title": "Batch Place Order",
    "permalink": "/usa-docs/v5/order/batch-place"
  },
  "next": {
    "title": "Batch Cancel Order",
    "permalink": "/usa-docs/v5/order/batch-cancel"
  }
}